drf_authjwt/__init__.py
drf_authjwt/admin.py
drf_authjwt/apps.py
drf_authjwt/models.py
drf_authjwt/serializers.py
drf_authjwt/tests.py
drf_authjwt/urls.py
drf_authjwt/views.py
drf_simple_auth_jwt-0.0.8.dist-info/LICENSE
drf_simple_auth_jwt-0.0.8.dist-info/METADATA
drf_simple_auth_jwt-0.0.8.dist-info/WHEEL
drf_simple_auth_jwt-0.0.8.dist-info/top_level.txt
drf_simple_auth_jwt-0.0.8.dist-info/RECORD
